{
	"clbid": 11734,
	"credits": 1.0,
	"crsid": 139,
	"depts": [
		"BIO"
	],
	"desc": "Ecology focuses on the study of the interrelationships that determine the distribution and abundance of organisms. This course examines organism-environment interactions and the study of populations, communities and ecosystems. Consideration is given to use of ecological studies in ecosystem management. Students attend lectures plus one 3-hour laboratory per week. Taught twice a year. Prerequisites: Biology 125 and 126.",
	"groupid": 139,
	"level": 200,
	"num": 261,
	"pf": false,
	"places": [
		"SC 280"
	],
	"profs": [
		"Daniel L. Hernandez"
	],
	"sem": 3,
	"term": 20053,
	"times": [
		"MWF 0905-1000"
	],
	"title": "Ecological Principles",
	"type": "Research",
	"year": 2005
}
