{
	"clbid": 11387,
	"credits": 1.0,
	"crsid": 436,
	"depts": [
		"ENGL"
	],
	"desc": "Students explore specific periods in American literature and examine the relationship between literary texts and movements and their particular cultural, political and historical contexts. Each offering of this course examines a different literary era and emphasizes specific literary and historical issues.",
	"level": 300,
	"name": "Adv Lit Era: 19th C Am",
	"num": 340,
	"pf": false,
	"places": [
		"RML 520"
	],
	"profs": [
		"Carol Holly"
	],
	"sem": 2,
	"term": 20052,
	"times": [
		"M-F 1040-1240PM"
	],
	"title": "Advanced Studies in Literary Eras: American",
	"type": "Topic",
	"year": 2005
}
