{
	"clbid": 99192,
	"credits": 0.25,
	"crsid": 999,
	"depts": [
		"ESAC"
	],
	"desc": "Students learn basic skills and techniques of in-line skating. Equipment is required for participation.",
	"gereqs": [
		"SPM"
	],
	"halfcredit": "2",
	"level": 100,
	"notes": "Second half of semester course.",
	"num": 108,
	"pf": false,
	"places": [
		"Tostrud Ctr"
	],
	"profs": [
		"William Sean Goldsworthy"
	],
	"sem": 3,
	"term": 20143,
	"times": [
		"MWF 0200-0255PM"
	],
	"title": "In-Line Skating",
	"type": "Research",
	"year": 2014
}
