{
	"clbid": 102093,
	"credits": 1.0,
	"crsid": 1186,
	"depts": [
		"PSYCH"
	],
	"desc": "Seminars allow in-depth study of particular themes or topics in psychology. See department Website for descriptions and additional prerequisites. Offered most years. May be repeated if topics are different. Prerequisite: PSYCH 230.",
	"instructors": [
		"Anna E. Johnson"
	],
	"level": 300,
	"locations": [
		"RNS 206"
	],
	"name": "Sem: Stress and Development",
	"num": 390,
	"pf": false,
	"prerequisites": "Prerequisite: PSYCH 230.",
	"revisions": [
		{
			"_updated": "2015-04-07T16:54:39.481099-05:00",
			"locations": [
				"RNS 208"
			]
		},
		{
			"_updated": "2015-09-29T00:01:43.268478-05:00",
			"status": "O"
		}
	],
	"section": "B",
	"semester": 3,
	"status": "C",
	"term": 20153,
	"times": [
		"MWF 0200-0255PM"
	],
	"title": "Issues in Psychology",
	"type": "Seminar",
	"year": 2015
}
