{
	"clbid": 75110,
	"credits": 1.0,
	"crsid": 1194,
	"depts": [
		"REL"
	],
	"desc": "This course treats the major moments of theology by focusing on five or six important theological figures, movements or texts spanning ancient, medieval and modern Christian theology. Prerequisite: BTS-B.",
	"gereqs": [
		"BTS-T"
	],
	"level": 200,
	"num": 203,
	"pf": false,
	"places": [
		"DC 204"
	],
	"profs": [
		"Mary E. Anderson"
	],
	"sem": 4,
	"term": 20094,
	"times": [
		"M-F 1000-1130"
	],
	"title": "The Greats",
	"type": "Research",
	"year": 2009
}
