{
	"clbid": 80712,
	"credits": 1.0,
	"crsid": 24137,
	"depts": [
		"HIST"
	],
	"desc": "How do Cubans view their past, and how does this shape their understanding of the present? This course focuses on the 1959 Revolution and historical memory. Students explore through visits to museums, memorials, and monuments how the government has sought to influence the ways Cubans remember the revolution and the later turn toward socialism. Students also study present-day Cuba through visits to health clinics, cooperatives, and schools, as well as lectures from local experts. Offered in alternate years during Interim.",
	"gereqs": [
		"MCG"
	],
	"level": 200,
	"notes": "This is an off-campus course.",
	"num": 244,
	"pf": false,
	"profs": [
		"Jeane DeLaney"
	],
	"sem": 2,
	"term": 20112,
	"title": "Revolutionary Cuba",
	"type": "Research",
	"year": 2011
}
