{
	"clbid": 80759,
	"credits": 1.0,
	"crsid": 17715,
	"depts": [
		"IS"
	],
	"desc": "Igor Stravinsky said that film music should have \"the same relationship to the film drama that somebody's piano playing in my living room has on the book I am reading.\" In this seminar, students encounter an art that can have devastating emotional impact while often remaining unnoticed. Students achieve a broad understanding of the history of music in cinema and create new film music in team-based collaborations. No music background or other prerequisites required.",
	"gereqs": [
		"ALS-A",
		"ORC"
	],
	"level": 200,
	"notes": "Not open to first-year students.",
	"num": 214,
	"pf": false,
	"places": [
		"RNS 190"
	],
	"profs": [
		"Justin W. Merritt"
	],
	"sem": 3,
	"term": 20113,
	"times": [
		"MWF 0200-0255PM"
	],
	"title": "Top: Music in Film",
	"type": "Topic",
	"year": 2011
}
