{
	"clbid": 67833,
	"credits": 0.75,
	"crsid": 817,
	"depts": [
		"MUSIC"
	],
	"desc": "Continuing the theory sequence from 114, third-semester music majors explore Baroque counterpoint, Classical and Romantic styles and forms, advanced modulation techniques, and chromatic harmony. This course also introduces musical acoustics and music technology. Prerequisites: Music 112/114. Co-requisite: Music 211. Offered annually in the Fall Semester.",
	"level": 200,
	"num": 213,
	"pf": false,
	"places": [
		"CHM 239",
		"CHM 239"
	],
	"profs": [
		"Catherine R. Rodland"
	],
	"sect": "B",
	"sem": 1,
	"term": 20091,
	"times": [
		"T 0935-1100",
		"Th 0930-1050"
	],
	"title": "Theory III",
	"type": "Research",
	"year": 2009
}
