{
	"clbid": 90541,
	"credits": 1.0,
	"crsid": 1218,
	"depts": [
		"REL"
	],
	"desc": "This survey of the historical, cultural, and theological developments within Judaism pays special attention to major periods and themes in Jewish life and thought, as well as to contemporary Judaism. Prerequisite: sophomore status or higher. Open to first-year students with permission of the instructor.",
	"gereqs": [
		"HWC"
	],
	"level": 200,
	"num": 248,
	"pf": false,
	"places": [
		"OM 030",
		"OM 030"
	],
	"profs": [
		"Mara H. Benjamin"
	],
	"sem": 3,
	"term": 20133,
	"times": [
		"T 1145-0110PM",
		"Th 1245-0205PM"
	],
	"title": "Judaism",
	"type": "Research",
	"year": 2013
}
