{
	"clbid": 65564,
	"credits": 1.0,
	"crsid": 479,
	"depts": [
		"FREN"
	],
	"desc": "Students expand their ability to communicate in French, understand French texts and interpret French and U.S. cultures through study and discussion of specific social and cultural topics that are relevant (e.g. stereotypes, the family, education, immigration). Explicit focus on cross-cultural comparison/contrast and analysis. Students develop their ability to listen, speak, read and write, while paying particular attention to listening and reading strategies. Prerequisite: French 112 or placement. Offered Fall and Spring Semesters.",
	"level": 200,
	"name": "Intermed French I",
	"num": 231,
	"pf": false,
	"places": [
		"SC 130"
	],
	"profs": [
		"Amine R. Bekhechi"
	],
	"sect": "D",
	"sem": 1,
	"term": 20081,
	"times": [
		"MWF 1255-0150PM"
	],
	"title": "Intermediate French I",
	"type": "Research",
	"year": 2008
}
